{
  "$schema": "https://developer.microsoft.com/json-schemas/fabric/item/report/definition/visualContainer/2.9.0/schema.json",
  "name": "cfbcd038ae0830eb3182",
  "position": {
    "x": 21.22304825575753,
    "y": 97.54646840148699,
    "z": 8000,
    "height": 30.173410404624278,
    "width": 85.3179190751445,
    "tabOrder": 8000
  },
  "visual": {
    "visualType": "actionButton",
    "objects": {
      "icon": [
        {
          "properties": {
            "shapeType": {
              "expr": {
                "Literal": {
                  "Value": "'blank'"
                }
              }
            },
            "lineWeight": {
              "expr": {
                "Literal": {
                  "Value": "1L"
                }
              }
            }
          },
          "selector": {
            "id": "default"
          }
        }
      ],
      "text": [
        {
          "properties": {
            "show": {
              "expr": {
                "Literal": {
                  "Value": "true"
                }
              }
            }
          }
        },
        {
          "properties": {
            "text": {
              "expr": {
                "Literal": {
                  "Value": "'Financial Year'"
                }
              }
            },
            "bold": {
              "expr": {
                "Literal": {
                  "Value": "false"
                }
              }
            },
            "fontColor": {
              "solid": {
                "color": {
                  "expr": {
                    "ThemeDataColor": {
                      "ColorId": 0,
                      "Percent": 0
                    }
                  }
                }
              }
            },
            "leftMargin": {
              "expr": {
                "Literal": {
                  "Value": "1L"
                }
              }
            },
            "topMargin": {
              "expr": {
                "Literal": {
                  "Value": "1L"
                }
              }
            },
            "bottomMargin": {
              "expr": {
                "Literal": {
                  "Value": "1L"
                }
              }
            },
            "rightMargin": {
              "expr": {
                "Literal": {
                  "Value": "1L"
                }
              }
            },
            "fontSize": {
              "expr": {
                "Literal": {
                  "Value": "8D"
                }
              }
            }
          },
          "selector": {
            "id": "default"
          }
        }
      ],
      "fill": [
        {
          "properties": {
            "show": {
              "expr": {
                "Literal": {
                  "Value": "true"
                }
              }
            }
          }
        },
        {
          "properties": {
            "fillColor": {
              "solid": {
                "color": {
                  "expr": {
                    "Literal": {
                      "Value": "'#333333'"
                    }
                  }
                }
              }
            },
            "transparency": {
              "expr": {
                "Literal": {
                  "Value": "10D"
                }
              }
            }
          },
          "selector": {
            "id": "default"
          }
        },
        {
          "properties": {
            "fillColor": {
              "solid": {
                "color": {
                  "expr": {
                    "ThemeDataColor": {
                      "ColorId": 1,
                      "Percent": 0.2
                    }
                  }
                }
              }
            }
          },
          "selector": {
            "id": "selected"
          }
        }
      ],
      "outline": [
        {
          "properties": {
            "weight": {
              "expr": {
                "Literal": {
                  "Value": "0.5D"
                }
              }
            }
          },
          "selector": {
            "id": "selected"
          }
        },
        {
          "properties": {
            "weight": {
              "expr": {
                "Literal": {
                  "Value": "1D"
                }
              }
            }
          },
          "selector": {
            "id": "default"
          }
        }
      ]
    },
    "visualContainerObjects": {
      "visualLink": [
        {
          "properties": {
            "show": {
              "expr": {
                "Literal": {
                  "Value": "true"
                }
              }
            },
            "type": {
              "expr": {
                "Literal": {
                  "Value": "'PageNavigation'"
                }
              }
            },
            "navigationSection": {
              "expr": {
                "Literal": {
                  "Value": "'2f98f1a445d1d65ac3ea'"
                }
              }
            }
          }
        }
      ]
    },
    "drillFilterOtherVisuals": true
  },
  "howCreated": "InsertVisualButton"
}